LICENSE
MANIFEST.in
README.md
README.rst
setup.py
neutrino_api/__init__.py
neutrino_api/api_helper.py
neutrino_api/configuration.py
neutrino_api/decorators.py
neutrino_api/neutrino_api_client.py
neutrino_api.egg-info/PKG-INFO
neutrino_api.egg-info/SOURCES.txt
neutrino_api.egg-info/dependency_links.txt
neutrino_api.egg-info/requires.txt
neutrino_api.egg-info/top_level.txt
neutrino_api/controllers/__init__.py
neutrino_api/controllers/base_controller.py
neutrino_api/controllers/data_tools.py
neutrino_api/controllers/e_commerce.py
neutrino_api/controllers/geolocation.py
neutrino_api/controllers/imaging.py
neutrino_api/controllers/security_and_networking.py
neutrino_api/controllers/telephony.py
neutrino_api/controllers/www.py
neutrino_api/exceptions/__init__.py
neutrino_api/exceptions/api_error_exception.py
neutrino_api/exceptions/api_exception.py
neutrino_api/http/__init__.py
neutrino_api/http/http_call_back.py
neutrino_api/http/http_client.py
neutrino_api/http/http_context.py
neutrino_api/http/http_method_enum.py
neutrino_api/http/http_request.py
neutrino_api/http/http_response.py
neutrino_api/http/requests_client.py
neutrino_api/http/auth/__init__.py
neutrino_api/http/auth/custom_query_auth.py
neutrino_api/models/__init__.py
neutrino_api/models/bad_word_filter_response.py
neutrino_api/models/bin_lookup_response.py
neutrino_api/models/blacklist.py
neutrino_api/models/browser_bot_response.py
neutrino_api/models/convert_response.py
neutrino_api/models/email_validate_response.py
neutrino_api/models/email_verify_response.py
neutrino_api/models/geocode_address_response.py
neutrino_api/models/geocode_reverse_response.py
neutrino_api/models/hlr_lookup_response.py
neutrino_api/models/host_reputation_response.py
neutrino_api/models/ip_blocklist_response.py
neutrino_api/models/ip_info_response.py
neutrino_api/models/ip_probe_response.py
neutrino_api/models/location.py
neutrino_api/models/phone_playback_response.py
neutrino_api/models/phone_validate_response.py
neutrino_api/models/phone_verify_response.py
neutrino_api/models/sms_message_response.py
neutrino_api/models/sms_verify_response.py
neutrino_api/models/url_info_response.py
