Metadata-Version: 2.1
Name: neutrino-api
Version: 3.4.5
Summary: The general-purpose API
Home-page: https://www.neutrinoapi.com/
Author: Neutrino API
Author-email: tech@neutrinoapi.com
License: UNKNOWN
Platform: UNKNOWN
